reg_file.v
module regfile(IN, OUT1, OUT2, INADDRESS, OUT1ADDRESS, OUT2ADDRESS, WRITE, CLK, RESET);
    input [7:0] IN;
    input [2:0] INADDRESS, OUT1ADDRESS, OUT2ADDRESS;
    input WRITE, CLK, RESET;
    output reg [7:0] OUT1, OUT2;
    integer i;
    reg [7:0] regArray [0:7];
    
    always @(*) begin

        case(OUT1ADDRESS)
            3'b000: OUT1<= #2 regArray[0];
            3'b001: OUT1<= #2 regArray[1];
            3'b010: OUT1<= #2 regArray[2];
            3'b011: OUT1<= #2 regArray[3];
            3'b100: OUT1<= #2 regArray[4];
            3'b101: OUT1<= #2 regArray[5];
            3'b110: OUT1<= #2 regArray[6];
            3'b111: OUT1<= #2 regArray[7];
        endcase

        case(OUT2ADDRESS)
            3'b000: OUT2<= #2 regArray[0];
            3'b001: OUT2<= #2 regArray[1];
            3'b010: OUT2<= #2 regArray[2];
            3'b011: OUT2<= #2 regArray[3];
            3'b100: OUT2<= #2 regArray[4];
            3'b101: OUT2<= #2 regArray[5];
            3'b110: OUT2<= #2 regArray[6];
            3'b111: OUT2<= #2 regArray[7];
        endcase
    end

    always @ (posedge CLK)
    begin
        if(WRITE)begin
            case(INADDRESS)
                3'b000: regArray[0]<= #1 IN;
                3'b001: regArray[1]<= #1 IN;
                3'b010: regArray[2]<= #1 IN;
                3'b011: regArray[3]<= #1 IN;
                3'b100: regArray[4]<= #1 IN;
                3'b101: regArray[5]<= #1 IN;
                3'b110: regArray[6]<= #1 IN;
                3'b111: regArray[7]<= #1 IN;
            endcase
        end
        if(RESET)begin
            for (i = 0; i < 8; i = i + 1) begin
                regArray[i] <= #1 8'h00;
            end
        end
    end
endmodule

regfile_tb.v
module regfile_tb;

    // Inputs
    reg [7:0] IN;
    reg [2:0] INADDRESS, OUT1ADDRESS, OUT2ADDRESS;
    reg WRITE, CLK, RESET;

    // Outputs
    wire [7:0] OUT1, OUT2;

    // Instantiate the regfile module
    regfile uut (IN, OUT1, OUT2, INADDRESS, OUT1ADDRESS, OUT2ADDRESS, WRITE, CLK, RESET);

    // Clock generation
    always begin
        #5 CLK = ~CLK; // Toggle clock every 5 time units
    end

    initial begin
        $dumpfile("reg_file_wavedata.vcd");
		$dumpvars(0, regfile_tb);
        // Initialize Inputs
        IN = 8'b00000000;
        INADDRESS = 3'b000;
        OUT1ADDRESS = 3'b000;
        OUT2ADDRESS = 3'b000;
        WRITE = 0;
        CLK = 0;
        RESET = 0;

        // Wait for global reset to finish
        #10;

        // Reset the register file
        RESET = 1;
        #10;
        RESET = 0;
        #10;

        // Write data to register 3
        IN = 8'b10101010;
        INADDRESS = 3'b011;
        WRITE = 1;
        #10;
        WRITE = 0;
        #10;

        // Read data from register 3 to OUT1
        OUT1ADDRESS = 3'b011;
        #10;
        $display("OUT1 (from reg 3): %b", OUT1);

        // Write data to register 5
        IN = 8'b01010101;
        INADDRESS = 3'b101;
        WRITE = 1;
        #10;
        WRITE = 0;
        #10;

        // Read data from register 5 to OUT2
        OUT2ADDRESS = 3'b101;
        #10;
        $display("OUT2 (from reg 5): %b", OUT2);

        // Reset the register file again
        RESET = 1;
        #10;
        RESET = 0;
        #10;

        // Read data from register 3 and 5 after reset
        #10;
        $display("OUT1 (after reset): %b", OUT1);
        $display("OUT2 (after reset): %b", OUT2);

        // Finish the test
        $finish;
    end

endmodule

reg_file_wavedata.vcd
$date
	Mon May 20 17:05:46 2024
$end
$version
	Icarus Verilog
$end
$timescale
	1s
$end
$scope module regfile_tb $end
$var wire 8 ! OUT2 [7:0] $end
$var wire 8 " OUT1 [7:0] $end
$var reg 1 # CLK $end
$var reg 8 $ IN [7:0] $end
$var reg 3 % INADDRESS [2:0] $end
$var reg 3 & OUT1ADDRESS [2:0] $end
$var reg 3 ' OUT2ADDRESS [2:0] $end
$var reg 1 ( RESET $end
$var reg 1 ) WRITE $end
$scope module uut $end
$var wire 1 # CLK $end
$var wire 8 * IN [7:0] $end
$var wire 3 + INADDRESS [2:0] $end
$var wire 3 , OUT1ADDRESS [2:0] $end
$var wire 3 - OUT2ADDRESS [2:0] $end
$var wire 1 ( RESET $end
$var wire 1 ) WRITE $end
$var reg 8 . OUT1 [7:0] $end
$var reg 8 / OUT2 [7:0] $end
$var integer 32 0 i [31:0] $end
$upscope $end
$upscope $end
$enddefinitions $end
$comment Show the parameter values. $end
$dumpall
$end
#0
$dumpvars
bx 0
bx /
bx .
b0 -
b0 ,
b0 +
b0 *
0)
0(
b0 '
b0 &
b0 %
b0 $
0#
bx "
bx !
$end
#5
1#
#10
0#
1(
#15
b1000 0
1#
#18
b0 !
b0 /
b0 "
b0 .
#20
0#
0(
#25
1#
#30
0#
1)
b11 %
b11 +
b10101010 $
b10101010 *
#35
1#
#40
0#
0)
#45
1#
#50
0#
b11 &
b11 ,
#52
b10101010 "
b10101010 .
#55
1#
#60
0#
1)
b101 %
b101 +
b1010101 $
b1010101 *
#65
1#
#70
0#
0)
#75
1#
#80
0#
b101 '
b101 -
#82
b1010101 !
b1010101 /
#85
1#
#90
0#
1(
#95
b1000 0
1#
#98
b0 !
b0 /
b0 "
b0 .
#100
0#
0(
